napari_brainbow_diagnose/__init__.py
napari_brainbow_diagnose/_density.py
napari_brainbow_diagnose/_matplotlib_utils.py
napari_brainbow_diagnose/_read_csv_widget.py
napari_brainbow_diagnose/_sample_data.py
napari_brainbow_diagnose/_tooltip_pointer.py
napari_brainbow_diagnose/_utils_channel_space.py
napari_brainbow_diagnose/_utils_image.py
napari_brainbow_diagnose/_utils_io.py
napari_brainbow_diagnose/_utils_shape.py
napari_brainbow_diagnose/_utils_widget.py
napari_brainbow_diagnose/_version.py
napari_brainbow_diagnose/_widget.py
napari_brainbow_diagnose/napari.yaml
napari_brainbow_diagnose/_tests/__init__.py
napari_brainbow_diagnose/_tests/test_sample_data.py
napari_brainbow_diagnose/_tests/test_utils_shape.py
napari_brainbow_diagnose/_tests/test_widget.py
napari_brainbow_diagnose-0.2.0.dist-info/LICENSE
napari_brainbow_diagnose-0.2.0.dist-info/METADATA
napari_brainbow_diagnose-0.2.0.dist-info/WHEEL
napari_brainbow_diagnose-0.2.0.dist-info/entry_points.txt
napari_brainbow_diagnose-0.2.0.dist-info/top_level.txt
napari_brainbow_diagnose-0.2.0.dist-info/RECORD
