Metadata-Version: 2.2
Name: napari-brainbow-diagnose
Version: 0.2.0
Summary: Visualize and Diagnose brainbow dataset in color space.
Home-page: https://github.com/LaboratoryOpticsBiosciences/napari-brainbow-diagnose
Author: Clement Caporal
Author-email: clement.caporal@polytechnique.edu
License: BSD-3-Clause
Project-URL: Bug Tracker, https://github.com/LaboratoryOpticsBiosciences/napari-brainbow-diagnose/issues
Project-URL: Documentation, https://github.com/LaboratoryOpticsBiosciences/napari-brainbow-diagnose#README.md
Project-URL: Source Code, https://github.com/LaboratoryOpticsBiosciences/napari-brainbow-diagnose
Project-URL: User Support, https://github.com/LaboratoryOpticsBiosciences/napari-brainbow-diagnose/issues
Classifier: Development Status :: 2 - Pre-Alpha
Classifier: Framework :: napari
Classifier: Intended Audience :: Developers
Classifier: License :: OSI Approved :: BSD License
Classifier: Operating System :: OS Independent
Classifier: Programming Language :: Python
Classifier: Programming Language :: Python :: 3
Classifier: Programming Language :: Python :: 3 :: Only
Classifier: Programming Language :: Python :: 3.8
Classifier: Programming Language :: Python :: 3.9
Classifier: Programming Language :: Python :: 3.10
Classifier: Topic :: Scientific/Engineering :: Image Processing
Requires-Python: >=3.8
License-File: LICENSE
Requires-Dist: numpy
Requires-Dist: magicgui
Requires-Dist: pooch
Requires-Dist: matplotlib
Requires-Dist: scikit-image
Provides-Extra: testing
Requires-Dist: tox; extra == "testing"
Requires-Dist: pytest; extra == "testing"
Requires-Dist: pytest-cov; extra == "testing"
Requires-Dist: pytest-qt; extra == "testing"
Requires-Dist: pre-commit; extra == "testing"
Requires-Dist: napari; extra == "testing"
Requires-Dist: pyqt5; extra == "testing"
